rtl/top_soc.v
module top_soc (
    input clk,
    input reset,
    output reg [7:0] counter
  );

  always @(posedge clk)
  begin
    if (reset)
      counter <= 8'b0;
    else
      counter <= counter + 1'b1;
  end

endmodule

sim/waveforms/dump.vcd
$version Generated by VerilatedVcd $end
$timescale 1ps $end
 $scope module TOP $end
  $var wire 1 # clk $end
  $var wire 1 $ reset $end
  $var wire 8 % counter [7:0] $end
  $scope module top_soc $end
   $var wire 1 # clk $end
   $var wire 1 $ reset $end
   $var wire 8 % counter [7:0] $end
  $upscope $end
 $upscope $end
$enddefinitions $end


#0
1#
1$
b00000000 %
#1
0#
#2
1#
#3
0#
#4
1#
#5
0#
#6
1#
#7
0#
#8
1#
#9
0#
#10
1#
#11
0#
0$
#12
1#
b00000001 %
#13
0#
#14
1#
b00000010 %
#15
0#
#16
1#
b00000011 %
#17
0#
#18
1#
b00000100 %
#19
0#
#20
1#
b00000101 %
#21
0#
#22
1#
b00000110 %
#23
0#
#24
1#
b00000111 %
#25
0#
#26
1#
b00001000 %
#27
0#
#28
1#
b00001001 %
#29
0#
#30
1#
b00001010 %
#31
0#
#32
1#
b00001011 %
#33
0#
#34
1#
b00001100 %
#35
0#
#36
1#
b00001101 %
#37
0#
#38
1#
b00001110 %
#39
0#
#40
1#
b00001111 %
#41
0#
#42
1#
b00010000 %
#43
0#
#44
1#
b00010001 %
#45
0#
#46
1#
b00010010 %
#47
0#
#48
1#
b00010011 %
#49
0#
#50
1#
b00010100 %
#51
0#
#52
1#
b00010101 %
#53
0#
#54
1#
b00010110 %
#55
0#
#56
1#
b00010111 %
#57
0#
#58
1#
b00011000 %
#59
0#
#60
1#
b00011001 %
#61
0#
#62
1#
b00011010 %
#63
0#
#64
1#
b00011011 %
#65
0#
#66
1#
b00011100 %
#67
0#
#68
1#
b00011101 %
#69
0#
#70
1#
b00011110 %
#71
0#
#72
1#
b00011111 %
#73
0#
#74
1#
b00100000 %
#75
0#
#76
1#
b00100001 %
#77
0#
#78
1#
b00100010 %
#79
0#
#80
1#
b00100011 %
#81
0#
#82
1#
b00100100 %
#83
0#
#84
1#
b00100101 %
#85
0#
#86
1#
b00100110 %
#87
0#
#88
1#
b00100111 %
#89
0#
#90
1#
b00101000 %
#91
0#
#92
1#
b00101001 %
#93
0#
#94
1#
b00101010 %
#95
0#
#96
1#
b00101011 %
#97
0#
#98
1#
b00101100 %
